Metadata-Version: 2.1
Name: hdsr-fewspy
Version: 1.17
Summary: A python project to request data (locations, time-series, etc.) from a HDSR FEWS PiWebService
Home-page: https://github.com/hdsr-mid/hdsr_fewspy
Download-URL: https://github.com/hdsr-mid/hdsr_fewspy/archive/v1.17.tar.gz
Author: Renier Kramer
Author-email: renier.kramer@hdsr.nl
Maintainer: Roger de Crook
Maintainer-email: roger.de.crook@hdsr.nl
License: MIT
Keywords: hdsr,fews,api,fewspy,wis
Classifier: Development Status :: 5 - Production/Stable
Classifier: Intended Audience :: Developers
Classifier: Topic :: Software Development :: Build Tools
Classifier: License :: OSI Approved :: MIT License
Classifier: Programming Language :: Python :: 3.7
Classifier: Programming Language :: Python :: 3.8
Classifier: Programming Language :: Python :: 3.9
Classifier: Programming Language :: Python :: 3.10
Classifier: Programming Language :: Python :: 3.11
Classifier: Programming Language :: Python :: 3.12
Requires-Python: >=3.7
License-File: LICENSE.txt
Requires-Dist: requests
Requires-Dist: geopandas
Requires-Dist: pandas
Requires-Dist: hdsr-pygithub
Provides-Extra: test
Requires-Dist: pytest; extra == "test"
